src/__init__.py
src/config/callbacks/default_callbacks.yaml
src/config/callbacks/extended_callbacks.yaml
src/config/config.yaml
src/config/logging/comet_ml.yaml
src/config/logging/loggers.yaml
src/config/logging/wandb.yaml
src/config/loss/bce_logits.yaml
src/config/loss/cross_entropy.yaml
src/config/loss/cutmix.yaml
src/config/loss/huber.yaml
src/config/loss/mae.yaml
src/config/loss/mixup.yaml
src/config/loss/mse.yaml
src/config/loss/smoothl1loss.yaml
src/config/loss/ventilator.yaml
src/config/model/cnn.yaml
src/config/model/gradient_boosting.yaml
src/config/model/mlp.yaml
src/config/model/rnn.yaml
src/config/model/transformer.yaml
src/config/optimizer/adabelief.yaml
src/config/optimizer/adabound.yaml
src/config/optimizer/adadelta.yaml
src/config/optimizer/adagrad.yaml
src/config/optimizer/adam.yaml
src/config/optimizer/adamax.yaml
src/config/optimizer/adamw.yaml
src/config/optimizer/adamwschedulefree.yaml
src/config/optimizer/adan.yaml
src/config/optimizer/asgd.yaml
src/config/optimizer/novograd.yaml
src/config/optimizer/rangeradabelief.yaml
src/config/optimizer/rmsprop.yaml
src/config/optimizer/rprop.yaml
src/config/optimizer/sgd.yaml
src/config/optimizer/sgdschedulefree.yaml
src/config/scheduler/cosine.yaml
src/config/scheduler/cosinewarm.yaml
src/config/scheduler/cyclic.yaml
src/config/scheduler/exponential.yaml
src/config/scheduler/lambda.yaml
src/config/scheduler/linearwithwarmup.yaml
src/config/scheduler/multi_step_reg.yaml
src/config/scheduler/onecycle.yaml
src/config/scheduler/plateau.yaml
src/config/scheduler/step.yaml
src/config/trainer/default_trainer.yaml
src/lightning_model.py
src/mlflow-init-commands.sh
src/models/__init__.py
src/models/autoencoder.py
src/models/cnn.py
src/models/gradient_boosting.py
src/models/mlp.py
src/models/rnn.py
src/models/transformer.py
src/preprocessing.py
src/train.py
src/utils/__init__.py
src/utils/dev.py
src/utils/metrics.py
src/utils/protein_task.py
airi_test_task-0.1.0.dist-info/LICENSE
airi_test_task-0.1.0.dist-info/METADATA
airi_test_task-0.1.0.dist-info/WHEEL
airi_test_task-0.1.0.dist-info/RECORD
